shellfuncs/__init__.py
shellfuncs/core.py
shellfuncs-0.2.1.dist-info/DESCRIPTION.rst
shellfuncs-0.2.1.dist-info/METADATA
shellfuncs-0.2.1.dist-info/RECORD
shellfuncs-0.2.1.dist-info/WHEEL
shellfuncs-0.2.1.dist-info/metadata.json
shellfuncs-0.2.1.dist-info/top_level.txt
